[{"timestamp":"2024-02-01T20:59:50.573Z","count":0,"uniques":0},{"timestamp":"2024-03-01T20:59:50.573Z","count":0,"uniques":0},{"timestamp":"2024-04-01T20:59:50.573Z","count":0,"uniques":0},{"timestamp":"2024-05-01T12:26:01.202Z","count":3,"uniques":3},{"timestamp":"2024-06-01T06:17:37.139Z","count":13,"uniques":5},{"timestamp":"2024-07-01T18:19:01.384Z","count":10,"uniques":4},{"timestamp":"2024-08-01T01:04:44.235Z","count":10,"uniques":6},{"timestamp":"2024-09-01T01:08:09.741Z","count":0,"uniques":0},{"timestamp":"2024-10-01T01:09:42.911Z","count":1,"uniques":1},{"timestamp":"2024-11-01T12:29:41.009Z","count":12,"uniques":3},{"timestamp":"2024-12-01T01:11:08.819Z","count":27,"uniques":6},{"timestamp":"2025-01-01T01:09:09.325Z","count":18,"uniques":4},{"timestamp":"2025-02-01T01:11:23.550Z","count":6,"uniques":2}]
